_base.so
_control.so
_geometric.so
_tools.so
_util.so
libompl.so
libompl.so.1.8.0
libompl.so.19
ompl/__init__.py
ompl/bindings_generator.py
ompl/base/__init__.py
ompl/base/_base.so
ompl/control/__init__.py
ompl/control/_control.so
ompl/geometric/__init__.py
ompl/geometric/_geometric.so
ompl/tools/__init__.py
ompl/tools/_tools.so
ompl/util/__init__.py
ompl/util/_util.so
ompl_genesis.libs/libboost_container-c6b946a2.so.1.87.0
ompl_genesis.libs/libboost_graph-6c427e27.so.1.87.0
ompl_genesis.libs/libboost_numpy313-5f3e71c8.so.1.87.0
ompl_genesis.libs/libboost_python313-19a2597b.so.1.87.0
ompl_genesis.libs/libboost_serialization-d3ad8370.so.1.87.0
ompl_genesis.libs/libompl-9b5ae863.so.1.8.0
ompl_genesis-1.7.1.dist-info/METADATA
ompl_genesis-1.7.1.dist-info/WHEEL
ompl_genesis-1.7.1.dist-info/top_level.txt
ompl_genesis-1.7.1.dist-info/RECORD
