Metadata-Version: 2.4
Name: ompl-genesis
Version: 1.7.1
Summary: The Open Motion Planning Library
Home-page: https://ompl.kavrakilab.org
Author: Ioan A. Șucan, Mark Moll, Zachary Kingston, Lydia E. Kavraki
Author-email: zak@rice.edu
Dynamic: author
Dynamic: author-email
Dynamic: home-page
Dynamic: summary
